djiffy/__init__.py
djiffy/admin.py
djiffy/apps.py
djiffy/importer.py
djiffy/models.py
djiffy/test_urls.py
djiffy/tests.py
djiffy/urls.py
djiffy/views.py
djiffy/fixtures/cc_by_nc_nd.rdf
djiffy/fixtures/chto-manifest.json
djiffy/fixtures/cotsen-collection-manifest.json
djiffy/fixtures/manifest-noseq.json
djiffy/fixtures/rightsstatement_org_NKC.json
djiffy/management/__init__.py
djiffy/management/commands/__init__.py
djiffy/management/commands/import_manifest.py
djiffy/migrations/0001_squashed_0004_migrate_jsonfield.py
djiffy/migrations/__init__.py
djiffy/static/css/djiffy.css
djiffy/static/img/creativecommons/by-nc-nd.svg
djiffy/static/img/creativecommons/by-nc.svg
djiffy/static/img/creativecommons/by-nd.svg
djiffy/static/img/creativecommons/by-sa.svg
djiffy/static/img/creativecommons/by.svg
djiffy/static/img/creativecommons/cc-zero.svg
djiffy/static/img/creativecommons/publicdomain.svg
djiffy/static/img/rightsstatements_org/CNE.svg
djiffy/static/img/rightsstatements_org/InC-EDU.svg
djiffy/static/img/rightsstatements_org/InC-NC.svg
djiffy/static/img/rightsstatements_org/InC-OW-EU.svg
djiffy/static/img/rightsstatements_org/InC-RUU.svg
djiffy/static/img/rightsstatements_org/InC.svg
djiffy/static/img/rightsstatements_org/NKC.svg
djiffy/static/img/rightsstatements_org/NoC-CR.svg
djiffy/static/img/rightsstatements_org/NoC-NC.svg
djiffy/static/img/rightsstatements_org/NoC-OKLR.svg
djiffy/static/img/rightsstatements_org/NoC-US.svg
djiffy/static/img/rightsstatements_org/UND.svg
djiffy/static/js/deepzoom.js
djiffy/static/js/openseadragon/LICENSE.txt
djiffy/static/js/openseadragon/changelog.txt
djiffy/static/js/openseadragon/openseadragon.js
djiffy/static/js/openseadragon/openseadragon.min.js
djiffy/static/js/openseadragon/openseadragon.min.js.map
djiffy/static/js/openseadragon/images/fullpage_grouphover.png
djiffy/static/js/openseadragon/images/fullpage_hover.png
djiffy/static/js/openseadragon/images/fullpage_pressed.png
djiffy/static/js/openseadragon/images/fullpage_rest.png
djiffy-1.0.2.dist-info/METADATA
djiffy-1.0.2.dist-info/WHEEL
djiffy-1.0.2.dist-info/licenses/LICENSE
djiffy-1.0.2.dist-info/RECORD
